README.rst
setup.py
postgresql_api/Table.py
postgresql_api/__init__.py
postgresql_api/api.py
postgresql_api/field_types.py
postgresql_api/main.py
postgresql_api.egg-info/PKG-INFO
postgresql_api.egg-info/SOURCES.txt
postgresql_api.egg-info/dependency_links.txt
postgresql_api.egg-info/requires.txt
postgresql_api.egg-info/top_level.txt