Metadata-Version: 1.1
Name: postgresql-api
Version: 2.0.0
Summary: API for postgresql
Home-page: https://github.com/AlexDev-py/postgresql_api.git
Author: AlexDev
Author-email: aleks.filiov@yandex.ru
License: MIT
Platform: UNKNOWN
Classifier: License :: OSI Approved :: MIT License
Classifier: Programming Language :: Python :: 3
